pyourls3/__init__.py
pyourls3/client.py
pyourls3/exceptions.py
tests/__init__.py
tests/sharevar.py
tests/test_expand.py
tests/test_init.py
tests/test_shorten.py
tests/test_stats.py
tests/test_url_stats.py
tests/webserver.py
pyourls3-1.0.1.dist-info/LICENSE
pyourls3-1.0.1.dist-info/METADATA
pyourls3-1.0.1.dist-info/WHEEL
pyourls3-1.0.1.dist-info/top_level.txt
pyourls3-1.0.1.dist-info/RECORD
