Metadata-Version: 2.1
Name: pyourls3
Version: 1.0.1
Summary: A Python 3 API wrapper for YOURLS
Home-page: https://www.tdpain.net/projects/pyourls3
Author: Thomas Pain
Author-email: pyourls3@tdpain.net
License: UNKNOWN
Platform: UNKNOWN
Classifier: Programming Language :: Python :: 3
Classifier: License :: OSI Approved :: Mozilla Public License 2.0 (MPL 2.0)
Classifier: Operating System :: OS Independent
Requires-Python: >=3.5
Requires-Dist: requests
Requires-Dist: certifi (>=2017.4.17)
Requires-Dist: chardet (<3.1.0,>=3.0.2)
Requires-Dist: idna (<2.9,>=2.5)
Requires-Dist: urllib3 (!=1.25.0,!=1.25.1,<1.26,>=1.21.1)
